odoo/addons/openupgrade_scripts/README.rst
odoo/addons/openupgrade_scripts/__init__.py
odoo/addons/openupgrade_scripts/__manifest__.py
odoo/addons/openupgrade_scripts/apriori.py
odoo/addons/openupgrade_scripts/readme/CONFIGURE.md
odoo/addons/openupgrade_scripts/readme/DESCRIPTION.md
odoo/addons/openupgrade_scripts/readme/INSTALL.md
odoo/addons/openupgrade_scripts/scripts/account/18.0.1.3/noupdate_changes.xml
odoo/addons/openupgrade_scripts/scripts/account/18.0.1.3/post-migration.py
odoo/addons/openupgrade_scripts/scripts/account/18.0.1.3/pre-migration.py
odoo/addons/openupgrade_scripts/scripts/account/18.0.1.3/upgrade_analysis.txt
odoo/addons/openupgrade_scripts/scripts/account/18.0.1.3/upgrade_analysis_work.txt
odoo/addons/openupgrade_scripts/scripts/account/tests/data.py
odoo/addons/openupgrade_scripts/scripts/account/tests/test_migration.py
odoo/addons/openupgrade_scripts/scripts/account_add_gln/18.0.1.0/upgrade_analysis.txt
odoo/addons/openupgrade_scripts/scripts/account_check_printing/18.0.1.0/upgrade_analysis.txt
odoo/addons/openupgrade_scripts/scripts/account_check_printing/18.0.1.0/upgrade_analysis_work.txt
odoo/addons/openupgrade_scripts/scripts/account_debit_note/18.0.1.0/pre-migration.py
odoo/addons/openupgrade_scripts/scripts/account_debit_note/18.0.1.0/upgrade_analysis.txt
odoo/addons/openupgrade_scripts/scripts/account_debit_note/18.0.1.0/upgrade_analysis_work.txt
odoo/addons/openupgrade_scripts/scripts/account_edi/18.0.1.0/upgrade_analysis.txt
odoo/addons/openupgrade_scripts/scripts/account_edi/18.0.1.0/upgrade_analysis_work.txt
odoo/addons/openupgrade_scripts/scripts/account_edi_proxy_client/18.0.1.0/upgrade_analysis.txt
odoo/addons/openupgrade_scripts/scripts/account_edi_ubl_cii/18.0.1.0/pre-migration.py
odoo/addons/openupgrade_scripts/scripts/account_edi_ubl_cii/18.0.1.0/upgrade_analysis.txt
odoo/addons/openupgrade_scripts/scripts/account_edi_ubl_cii/18.0.1.0/upgrade_analysis_work.txt
odoo_addon_openupgrade_scripts-18.0.1.0.0.454.dist-info/METADATA
odoo_addon_openupgrade_scripts-18.0.1.0.0.454.dist-info/WHEEL
odoo_addon_openupgrade_scripts-18.0.1.0.0.454.dist-info/top_level.txt
odoo_addon_openupgrade_scripts-18.0.1.0.0.454.dist-info/RECORD
