Metadata-Version: 2.1
Name: odoo-addon-openupgrade_scripts
Version: 18.0.1.0.0.454
Requires-Python: >=3.10
Requires-Dist: odoo==18.0.*
Requires-Dist: openupgradelib
Summary: Module that contains all the migrations analysis and scripts for migrate Odoo SA modules.
Home-page: https://github.com/OCA/OpenUpgrade
License: AGPL-3
Author: Odoo Community Association (OCA)
Author-email: support@odoo-community.org
Classifier: Programming Language :: Python
Classifier: Framework :: Odoo
Classifier: Framework :: Odoo :: 18.0
Classifier: License :: OSI Approved :: GNU Affero General Public License v3
